{
    "projectList": [
        {
            "name": "Pokedex",
            "status": "Desenvolvimento",
            "product": "Web",
            "startDate": "26/08/2022",
            "endDate": "-"
        },
        {
            "name": "Uber Clone",
            "status": "Concluído",
            "product": "Aplicativo",
            "startDate": "01/08/2022",
            "endDate": "01/08/2023"
        },
        {
            "name": "Pokedex",
            "status": "Desenvolvimento",
            "product": "Web",
            "startDate": "26/08/2022",
            "endDate": "-"
        },
        {
            "name": "Uber Clone",
            "status": "Concluído",
            "product": "Aplicativo",
            "startDate": "01/08/2022",
            "endDate": "01/08/2023"
        },
        {
            "name": "Pokedex",
            "status": "Desenvolvimento",
            "product": "Web",
            "startDate": "26/08/2022",
            "endDate": "-"
        },
        {
            "name": "Uber Clone",
            "status": "Concluído",
            "product": "Aplicativo",
            "startDate": "01/08/2022",
            "endDate": "01/08/2023"
        },
        {
            "name": "Pokedex",
            "status": "Desenvolvimento",
            "product": "Web",
            "startDate": "26/08/2022",
            "endDate": "-"
        }
    ]
}